#include "../include/operationMap.hpp"

using namespace std;

namespace OperationMap{
    bool create_map(map<uint8_t, string> &op_mapa){
        op_mapa[0X00] = "NOP";
        op_mapa[0X01] = "ACONST_NULL";
        op_mapa[0X02] = "ICONST_M1";
        op_mapa[0X03] = "ICONST_0";
        op_mapa[0X04] = "ICONST_1";
        op_mapa[0X05] = "ICONST_2";
        op_mapa[0X06] = "ICONST_3";
        op_mapa[0X07] = "ICONST_4";
        op_mapa[0X08] = "ICONST_5";
        op_mapa[0X09] = "LCONST_0";
        op_mapa[0X0A] = "LCONST_1";
        op_mapa[0X0B] = "FCONST_0";
        op_mapa[0X0C] = "FCONST_1";
        op_mapa[0X0D] = "FCONST_2";
        op_mapa[0X0E] = "DCONST_0";
        op_mapa[0X0F] = "DCONST_1";
        op_mapa[0X10] = "BIPUSH";
        op_mapa[0X11] = "SIPUSH";
        op_mapa[0X12] = "LDC";
        op_mapa[0X13] = "LDC_W";
        op_mapa[0X14] = "LDC2_W";
        op_mapa[0X15] = "ILOAD";
        op_mapa[0X16] = "LLOAD";
        op_mapa[0X17] = "FLOAD";
        op_mapa[0X18] = "DLOAD";
        op_mapa[0X19] = "ALOAD";
        op_mapa[0X1A] = "ILOAD_0";
        op_mapa[0X1B] = "ILOAD_1";
        op_mapa[0X1C] = "ILOAD_2";
        op_mapa[0X1D] = "ILOAD_3";
        op_mapa[0X1E] = "LLOAD_0";
        op_mapa[0X1F] = "LLOAD_1";
        op_mapa[0X20] = "LLOAD_2";
        op_mapa[0X21] = "LLOAD_3";
        op_mapa[0X22] = "FLOAD_0";
        op_mapa[0X23] = "FLOAD_1";
        op_mapa[0X24] = "FLOAD_2";
        op_mapa[0X25] = "FLOAD_3";
        op_mapa[0X26] = "DLOAD_0";
        op_mapa[0X27] = "DLOAD_1";
        op_mapa[0X28] = "DLOAD_2";
        op_mapa[0X29] = "DLOAD_3";
        op_mapa[0X2A] = "ALOAD_0";
        op_mapa[0X2B] = "ALOAD_1";
        op_mapa[0X2C] = "ALOAD_2";
        op_mapa[0X2D] = "ALOAD_3";
        op_mapa[0X2E] = "IALOAD";
        op_mapa[0X2F] = "LALOAD";
        op_mapa[0X30] = "FALOAD";
        op_mapa[0X31] = "DALOAD";
        op_mapa[0X32] = "AALOAD";
        op_mapa[0X33] = "BALOAD";
        op_mapa[0X34] = "CALOAD";
        op_mapa[0X35] = "SALOAD";
        op_mapa[0X36] = "ISTORE";
        op_mapa[0X37] = "LSTORE";
        op_mapa[0X38] = "FSTORE";
        op_mapa[0X39] = "DSTORE";
        op_mapa[0X3A] = "ASTORE";
        op_mapa[0X3B] = "ISTORE_0";
        op_mapa[0X3C] = "ISTORE_1";
        op_mapa[0X3D] = "ISTORE_2";
        op_mapa[0X3E] = "ISTORE_3";
        op_mapa[0X3F] = "LSTORE_0";
        op_mapa[0X40] = "LSTORE_1";
        op_mapa[0X41] = "LSTORE_2";
        op_mapa[0X42] = "LSTORE_3";
        op_mapa[0X43] = "FSTORE_0";
        op_mapa[0X44] = "FSTORE_1";
        op_mapa[0X45] = "FSTORE_2";
        op_mapa[0X46] = "FSTORE_3";
        op_mapa[0X47] = "DSTORE_0";
        op_mapa[0X48] = "DSTORE_1";
        op_mapa[0X49] = "DSTORE_2";
        op_mapa[0X4A] = "DSTORE_3";
        op_mapa[0X4B] = "ASTORE_0";
        op_mapa[0X4C] = "ASTORE_1";
        op_mapa[0X4D] = "ASTORE_2";
        op_mapa[0X4E] = "ASTORE_3";
        op_mapa[0X4F] = "IASTORE";
        op_mapa[0X50] = "LASTORE";
        op_mapa[0X51] = "FASTORE";
        op_mapa[0X52] = "DASTORE";
        op_mapa[0X53] = "AASTORE";
        op_mapa[0X54] = "BASTORE";
        op_mapa[0X55] = "CASTORE";
        op_mapa[0X56] = "SASTORE";
        op_mapa[0X57] = "POP";
        op_mapa[0X58] = "POP2";
        op_mapa[0X59] = "DUP";
        op_mapa[0X5A] = "DUP_X1";
        op_mapa[0X5B] = "DUP_X2";
        op_mapa[0X5C] = "DUP2";
        op_mapa[0X5D] = "DUP2_X1";
        op_mapa[0X5E] = "DUP2_X2";
        op_mapa[0X5F] = "SWAP";
        op_mapa[0X60] = "IADD";
        op_mapa[0X61] = "LADD";
        op_mapa[0X62] = "FADD";
        op_mapa[0X63] = "DADD";
        op_mapa[0X64] = "ISUB";
        op_mapa[0X65] = "LSUB";
        op_mapa[0X66] = "FSUB";
        op_mapa[0X67] = "DSUB";
        op_mapa[0X68] = "IMUL";
        op_mapa[0X69] = "LMUL";
        op_mapa[0X6A] = "FMUL";
        op_mapa[0X6B] = "DMUL";
        op_mapa[0X6C] = "IDIV";
        op_mapa[0X6D] = "LDIV";
        op_mapa[0X6E] = "FDIV";
        op_mapa[0X6F] = "DDIV";
        op_mapa[0X70] = "IREM";
        op_mapa[0X71] = "LREM";
        op_mapa[0X72] = "FREM";
        op_mapa[0X73] = "DREM";
        op_mapa[0X74] = "INEG";
        op_mapa[0X75] = "LNEG";
        op_mapa[0X76] = "FNEG";
        op_mapa[0X77] = "DNEG";
        op_mapa[0X78] = "ISHL";
        op_mapa[0X79] = "LSHL";
        op_mapa[0X7A] = "ISHR";
        op_mapa[0X7B] = "LSHR";
        op_mapa[0X7C] = "IUSHR";
        op_mapa[0X7D] = "LUSHR";
        op_mapa[0X7E] = "IAND";
        op_mapa[0X7F] = "LAND";
        op_mapa[0X80] = "IOR";
        op_mapa[0X81] = "LOR";
        op_mapa[0X82] = "IXOR";
        op_mapa[0X83] = "LXOR";
        op_mapa[0X84] = "IINC";
        op_mapa[0X85] = "I2L";
        op_mapa[0X86] = "I2F";
        op_mapa[0X87] = "I2D";
        op_mapa[0X88] = "L2I";
        op_mapa[0X89] = "L2F";
        op_mapa[0X8A] = "L2D";
        op_mapa[0X8B] = "F2I";
        op_mapa[0X8C] = "F2L";
        op_mapa[0X8D] = "F2D";
        op_mapa[0X8E] = "D2I";
        op_mapa[0X8F] = "D2L";
        op_mapa[0X90] = "D2F";
        op_mapa[0X91] = "I2B";
        op_mapa[0X92] = "I2C";
        op_mapa[0X93] = "I2S";
        op_mapa[0X94] = "LCMP";
        op_mapa[0X95] = "FCMPL";
        op_mapa[0X96] = "FCMPG";
        op_mapa[0X97] = "DCMPL";
        op_mapa[0X98] = "DCMPG";
        op_mapa[0X99] = "IFEQ";
        op_mapa[0X9A] = "IFNE";
        op_mapa[0X9B] = "IFLT";
        op_mapa[0X9C] = "IFGE";
        op_mapa[0X9D] = "IFGT";
        op_mapa[0X9E] = "IFLE";
        op_mapa[0X9F] = "IF_ICMPEQ";
        op_mapa[0XA0] = "IF_ICMPNE";
        op_mapa[0XA1] = "IF_ICMPLT";
        op_mapa[0XA2] = "IF_ICMPGE";
        op_mapa[0XA3] = "IF_ICMPGT";
        op_mapa[0XA4] = "IF_ICMPLE";
        op_mapa[0XA5] = "IF_ACMPEQ";
        op_mapa[0XA6] = "IF_ACMPNE";
        op_mapa[0XA7] = "GOTO";
        op_mapa[0XA8] = "JSR";
        op_mapa[0XA9] = "RET";
        op_mapa[0XAA] = "TABLESWITCH";
        op_mapa[0XAB] = "LOOKUPSWITCH";
        op_mapa[0XAC] = "IRETURN";
        op_mapa[0XAD] = "LRETURN";
        op_mapa[0XAE] = "FRETURN";
        op_mapa[0XAF] = "DRETURN";
        op_mapa[0XB0] = "ARETURN";
        op_mapa[0XB1] = "RETURN";
        op_mapa[0XB2] = "GETSTATIC";
        op_mapa[0XB3] = "PUTSTATIC";
        op_mapa[0XB4] = "GETFIELD";
        op_mapa[0XB5] = "PUTFIELD";
        op_mapa[0XB6] = "INVOKEVIRTUAL";
        op_mapa[0XB7] = "INVOKESPECIAL";
        op_mapa[0XB8] = "INVOKESTATIC";
        op_mapa[0XB9] = "INVOKEINTERFACE";
        op_mapa[0XBA] = "INVOKEDYNAMIC";
        op_mapa[0XBB] = "NEW";
        op_mapa[0XBC] = "NEWARRAY";
        op_mapa[0XBD] = "ANEWARRAY";
        op_mapa[0XBE] = "ARRAYLENGTH";
        op_mapa[0XBF] = "ATHROW";
        op_mapa[0XC0] = "CHECKCAST";
        op_mapa[0XC1] = "INSTANCEOF";
        op_mapa[0XC2] = "MONITORENTER";
        op_mapa[0XC3] = "MONITOREXIT";
        op_mapa[0XC4] = "WIDE";
        op_mapa[0XC5] = "MULTIANEWARRAY";
        op_mapa[0XC6] = "IFNULL";
        op_mapa[0XC7] = "IFNONNULL";
        op_mapa[0XC8] = "GOTO_W";
        op_mapa[0XC9] = "JSR_W";
        op_mapa[0XCA] = "BREAKPOINT";
        op_mapa[0XFE] = "IMPDEP1";
        op_mapa[0XFF] = "IMPDEP2";

        return true;
    }

    static map<uint8_t, string> op_mapa;
    static bool _dummy = create_map(op_mapa);


    std::string getOperation(uint8_t opcode){
        return(OperationMap::op_mapa[opcode]);
    }
}
